sphui/__init__.py
sphui/__main__.py
sphui/element.py
sphui/main.py
sphui/sph.py
sphui-0.3.dist-info/LICENSE
sphui-0.3.dist-info/METADATA
sphui-0.3.dist-info/WHEEL
sphui-0.3.dist-info/top_level.txt
sphui-0.3.dist-info/RECORD
